llmkira-1.0.5.dist-info/METADATA
llmkira-1.0.5.dist-info/WHEEL
llmkira-1.0.5.dist-info/licenses/LICENSE
llmkira-1.0.5.dist-info/licenses/NOTICE.MD
llmkira/__init__.py
llmkira/_exception.py
llmkira/cache/__init__.py
llmkira/cache/elara_runtime.py
llmkira/cache/lmdb_runtime.py
llmkira/cache/redis_runtime.py
llmkira/cache/runtime_schema.py
llmkira/doc_manager/__init__.py
llmkira/extra/plugins/__init__.py
llmkira/extra/plugins/alarm/__init__.py
llmkira/extra/plugins/e2b_code_interpreter/__init__.py
llmkira/extra/plugins/search/__init__.py
llmkira/extra/plugins/search/engine.py
llmkira/extra/voice/__init__.py
llmkira/extra/voice_hook.py
llmkira/kv_manager/__init__.py
llmkira/kv_manager/_base.py
llmkira/kv_manager/env.py
llmkira/kv_manager/file.py
llmkira/kv_manager/instruction.py
llmkira/kv_manager/time.py
llmkira/kv_manager/tool_call.py
llmkira/logic/__init__.py
llmkira/memory/__init__.py
llmkira/memory/_base.py
llmkira/memory/local_storage.py
llmkira/memory/redis_storage/LICENSE
llmkira/memory/redis_storage/__init__.py
llmkira/memory/redis_storage/utils.py
llmkira/openai/__init__.py
llmkira/openai/_excption.py
llmkira/openai/cell.py
llmkira/openai/request.py
llmkira/openai/utils.py
llmkira/openapi/__init__.py
llmkira/openapi/fuse/__init__.py
llmkira/openapi/hook/__init__.py
llmkira/openapi/trigger/__init__.py
llmkira/openapi/trigger/default_trigger.py
llmkira/sdk/__init__.py
llmkira/sdk/tools/LICENSE
llmkira/sdk/tools/__init__.py
llmkira/sdk/tools/error.py
llmkira/sdk/tools/loader.py
llmkira/sdk/tools/model.py
llmkira/sdk/tools/register.py
llmkira/sdk/tools/schema.py
llmkira/sdk/utils.py
llmkira/task/__init__.py
llmkira/task/schema.py
llmkira/task/snapshot/__init__.py
llmkira/task/snapshot/_base.py
llmkira/task/snapshot/local.py
llmkira-1.0.5.dist-info/RECORD
