Metadata-Version: 2.1
Name: llmkira
Version: 1.0.5
Summary: A chain message bot based on OpenAI
Keywords: llmbot,llmkira,openai,chatgpt,llm
Home-page: https://llmkira.github.io/Docs/
Author-Email: sudoskys <me@dianas.cyou>, llmkira <me@dianas.cyou>
License: Apache-2.0
Classifier: Programming Language :: Python :: 3
Classifier: Programming Language :: Python :: 3.9
Project-URL: Homepage, https://llmkira.github.io/Docs/
Project-URL: Repository, https://github.com/LlmKira/Openaibot
Requires-Python: <3.12,>=3.9
Requires-Dist: pathlib>=1.0.1
Requires-Dist: pydantic>=2.0.0
Requires-Dist: loguru>=0.5.3
Requires-Dist: httpx>=0.24.1
Requires-Dist: socksio<2.0.0,>=1.0.0
Requires-Dist: python-dotenv<2.0.0,>=1.0.0
Requires-Dist: redis>=4.5.4
Requires-Dist: aio-pika<10.0.0,>=9.3.0
Requires-Dist: arclet-alconna<2.0.0,>=1.7.26
Requires-Dist: shortuuid<2.0.0,>=1.0.11
Requires-Dist: tiktoken<1.0.0,>=0.5.1
Requires-Dist: contextvars<3.0,>=2.4
Requires-Dist: pytz<2024.0.0,>=2023.3.post1
Requires-Dist: numpy<2.0.0,>=1.24.0
Requires-Dist: fasttext-wheel<1.0.0,>=0.9.2
Requires-Dist: tenacity<9.0.0,>=8.2.3
Requires-Dist: pysocks<2.0.0,>=1.7.1
Requires-Dist: flask-sqlalchemy<4.0.0,>=3.1.1
Requires-Dist: emoji<3.0.0,>=2.8.0
Requires-Dist: websocket<1.0.0,>=0.2.1
Requires-Dist: wrapt<2.0.0,>=1.11.0
Requires-Dist: dynaconf<4.0.0,>=3.2.3
Requires-Dist: rich<14.0.0,>=13.6.0
Requires-Dist: importlib-metadata<7.0.0,>=6.8.0
Requires-Dist: sentry-sdk<2.0.0,>=1.34.0
Requires-Dist: boltons<24.0.0,>=23.1.1
Requires-Dist: orjson<4.0.0,>=3.9.10
Requires-Dist: pydantic-settings<3.0.0,>=2.0.3
Requires-Dist: docstring-parser<1.0,>=0.15
Requires-Dist: polling<1.0.0,>=0.3.2
Requires-Dist: elara<1.0.0,>=0.5.5
Requires-Dist: tzlocal<6.0,>=5.2
Requires-Dist: nltk<4.0.0,>=3.8.1
Requires-Dist: jieba<1.0.0,>=0.42.1
Requires-Dist: scikit-learn<2.0.0,>=1.3.2
Requires-Dist: cjieba<1.0.0,>=0.4.4
Requires-Dist: requests[socks]<3.0.0,>=2.31.0
Requires-Dist: feedparser<7.0.0,>=6.0.10
Requires-Dist: pillow<11.0.0,>=10.1.0
Requires-Dist: inscriptis<3.0.0,>=2.3.2
Requires-Dist: aiohttp<4.0.0,>=3.8.6
Requires-Dist: pytelegrambotapi<5.0.0,>=4.14.0
Requires-Dist: ffmpeg-python<1.0.0,>=0.2.0
Requires-Dist: duckduckgo-search>=5.3.0
Requires-Dist: flask<4.0.0,>=3.0.0
Requires-Dist: telegramify-markdown>=0.1.2
Requires-Dist: json-repair>=0.13.0
Requires-Dist: curl-cffi>=0.6.2
Requires-Dist: deprecated>=1.2.14
Requires-Dist: aiofile>=3.8.8
Requires-Dist: file-read-backwards>=3.0.0
Requires-Dist: apscheduler>=3.10.4
Requires-Dist: montydb[lmdb]>=2.5.2
Requires-Dist: pymongo>=4.6.3
Requires-Dist: fast-langdetect>=0.1.0
Requires-Dist: lmdb>=1.4.1
Requires-Dist: e2b>=0.14.14
Requires-Dist: e2b-code-interpreter>=0.0.3
Requires-Dist: gTTS>=2.5.1
Requires-Dist: hikari==2.0.0.dev121; extra == "bot"
Requires-Dist: hikari-crescent<1.0.0,>=0.6.4; extra == "bot"
Requires-Dist: khl-py<1.0.0,>=0.3.17; extra == "bot"
Requires-Dist: slack-bolt<2.0.0,>=1.18.0; extra == "bot"
Requires-Dist: hikari==2.0.0.dev121; extra == "testing"
Requires-Dist: hikari-crescent<1.0.0,>=0.6.4; extra == "testing"
Requires-Dist: khl-py<1.0.0,>=0.3.17; extra == "testing"
Requires-Dist: slack-bolt<2.0.0,>=1.18.0; extra == "testing"
Requires-Dist: pre-commit<3.5.0,>=2.15.0; extra == "testing"
Provides-Extra: bot
Provides-Extra: testing
